pytdd/__init__.py
pytdd/pytdd.py
pytdd-1.1.0.dist-info/LICENSE
pytdd-1.1.0.dist-info/METADATA
pytdd-1.1.0.dist-info/WHEEL
pytdd-1.1.0.dist-info/entry_points.txt
pytdd-1.1.0.dist-info/top_level.txt
pytdd-1.1.0.dist-info/RECORD
