Metadata-Version: 2.1
Name: pytdd
Version: 1.1.0
Summary: python TDD assistant, runs test command on source file change only
Home-page: https://gitlab.com/achauvinhameau/pytdd
Author: Alex Chauvin
Author-email: ach@meta-x.org
License: UNKNOWN
Platform: UNKNOWN
Classifier: Programming Language :: Python :: 3
Classifier: Programming Language :: Python :: 3.6
Classifier: Programming Language :: Python
Classifier: Intended Audience :: Developers
Classifier: Topic :: Software Development :: Testing
Requires-Python: >=3
Requires-Dist: watchdog
